HDF5_BLS_treat/__init__.py
HDF5_BLS_treat/errors.py
HDF5_BLS_treat/models.py
HDF5_BLS_treat/treat.py
HDF5_BLS_treat/treat_backend.py
hdf5_bls_treat-1.1.0.dist-info/METADATA
hdf5_bls_treat-1.1.0.dist-info/WHEEL
hdf5_bls_treat-1.1.0.dist-info/top_level.txt
hdf5_bls_treat-1.1.0.dist-info/RECORD
