Metadata-Version: 2.4
Name: HDF5_BLS_treat
Version: 1.1.0
Summary: A package to treat BLS power spectra densities and extract relevant infomration.
Author-email: Pierre Bouvet <pierre.bouvet@meduniwien.ac.at>
License-Expression: GPL-3.0-or-later
Project-URL: Homepage, https://github.com/bio-brillouin/HDF5_BLS
Project-URL: Documentation, https://hdf5-bls.readthedocs.io/en/latest/
Keywords: HDF5,Brillouin,BLS
Classifier: Programming Language :: Python :: 3
Classifier: Operating System :: OS Independent
Requires-Python: >=3.6
Requires-Dist: numpy
Requires-Dist: scipy>=1.10
Provides-Extra: dev
Requires-Dist: pytest; extra == "dev"
Provides-Extra: docs
Requires-Dist: sphinx; extra == "docs"
Requires-Dist: sphinx-rtd-theme; extra == "docs"
